pyini_parser/__init__.py
pyini_parser/configure/__init__.py
pyini_parser/configure/parser.py
pyini_parser/errors/__init__.py
pyini_parser/errors/error.py
pyini_parser-0.9.0.dist-info/WHEEL
pyini_parser-0.9.0.dist-info/METADATA
pyini_parser-0.9.0.dist-info/RECORD
