Metadata-Version: 2.1
Name: pyini-parser
Version: 0.9.0
Summary: 
Home-page: https://github.com/Mahmoud-Emad/ini-configuration-parser
License: MIT
Keywords: parser,ini,ini_parser,configuration
Author: Mahmoud Emad
Author-email: mahmmoud.hassanein@gmail.com
Requires-Python: >=3.8,<4.0
Classifier: License :: OSI Approved :: MIT License
Classifier: Programming Language :: Python :: 3
Classifier: Programming Language :: Python :: 3.10
Classifier: Programming Language :: Python :: 3.8
Classifier: Programming Language :: Python :: 3.9
Requires-Dist: pytest (>=7.1.2,<8.0.0)
Project-URL: Repository, https://github.com/Mahmoud-Emad/ini-configuration-parser
